{"inkVersion":21,"root":[[{"->":"start"},["done",{"#f":5,"#n":"g-0"}],null],"done",{"start":[["^Guidance Personel: Are you in need of counseling, student?","\n","ev","str","^ ","/str","/ev",{"*":".^.c-0","flg":20},{"c-0":["^ ",{"->":"continue_1"},"\n",{"#f":5}]}],{"#f":1}],"continue_1":[["^Guidance Personel: How can this humble office help you today?","\n","ev","str","^ ","/str","/ev",{"*":".^.c-0","flg":20},{"c-0":["^ ",{"->":"continue_2"},"\n",{"#f":5}]}],{"#f":1}],"continue_2":[["^Guidance Personel: This is the University Guidance Center.","\n","ev","str","^ ","/str","/ev",{"*":".^.c-0","flg":20},{"c-0":["^ ",{"->":"continue_3"},"\n",{"#f":5}]}],{"#f":1}],"continue_3":[["^Guidance Personel: Our office helps the university fulfill its mission and vision by supporting students’ growth and well-being.","\n","ev","str","^ ","/str","/ev",{"*":".^.c-0","flg":20},{"c-0":["^ ",{"->":"continue_4"},"\n",{"#f":5}]}],{"#f":1}],"continue_4":[["^Guidance Personel: We conceptualize, coordinate, and implement guidance programs across the different colleges.","\n","ev","str","^ ","/str","/ev",{"*":".^.c-0","flg":20},{"c-0":["^ ",{"->":"continue_5"},"\n",{"#f":5}]}],{"#f":1}],"continue_5":[["^Guidance Personel: Our goal is to develop well-balanced and mentally sound students through comprehensive and socially sensitive counseling services.","\n","ev","str","^ ","/str","/ev",{"*":".^.c-0","flg":20},{"c-0":["^ ",{"->":"continue_6"},"\n",{"#f":5}]}],{"#f":1}],"continue_6":[["^You: Hmmm… Can you guide me around the campus?","\n","ev","str","^ ","/str","/ev",{"*":".^.c-0","flg":20},{"c-0":["^ ",{"->":"continue_7"},"\n",{"#f":5}]}],{"#f":1}],"continue_7":[["^Guidance Personel: Haha! You need a different guide for that, student.","\n","ev","str","^ ","/str","/ev",{"*":".^.c-0","flg":20},{"c-0":["^ ",{"->":"continue_8"},"\n",{"#f":5}]}],{"#f":1}],"continue_8":[["^Guidance Personel: Be well on your way, and keep a sound mind.","\n","ev","str","^ ","/str","/ev",{"*":".^.c-0","flg":20},{"c-0":["^ ",{"->":"continue_9"},"\n",{"#f":5}]}],{"#f":1}],"continue_9":[["^Guidance Personel: Happy touring!","\n","ev","str","^ ","/str","/ev",{"*":".^.c-0","flg":20},{"c-0":["^ ","end","\n",{"#f":5}]}],{"#f":1}],"#f":1}],"listDefs":{}}